github_watchman/__about__.py
github_watchman/__init__.py
github_watchman/__main__.py
github_watchman/config.py
github_watchman/github_wrapper.py
github_watchman/logger.py
github_watchman/rules/access_tokens.yaml
github_watchman/rules/aws_api_tokens.yaml
github_watchman/rules/azure_api_tokens.yaml
github_watchman/rules/azure_service_account_files.yaml
github_watchman/rules/bearer_tokens.yaml
github_watchman/rules/client_secrets.yaml
github_watchman/rules/gcp_service_account_files.yaml
github_watchman/rules/google_api_tokens.yaml
github_watchman/rules/interesting_files.yaml
github_watchman/rules/misc_private_keys.yaml
github_watchman/rules/passwords.yaml
github_watchman/rules/pgp_private_keys.yaml
github_watchman/rules/private_tokens.yaml
github_watchman/rules/s3_config_files.yaml
github_watchman/rules/slack_api_tokens.yaml
github_watchman/rules/slack_webhooks.yaml
github_watchman-1.0.1.dist-info/LICENSE
github_watchman-1.0.1.dist-info/METADATA
github_watchman-1.0.1.dist-info/WHEEL
github_watchman-1.0.1.dist-info/entry_points.txt
github_watchman-1.0.1.dist-info/top_level.txt
github_watchman-1.0.1.dist-info/RECORD
