Metadata-Version: 2.1
Name: github-watchman
Version: 1.0.1
Summary: Monitoring GitHub for sensitive data shared publicly
Home-page: https://github.com/PaperMtn/github-watchman
Author: PaperMtn
Author-email: papermtn@protonmail.com
License: GPL-3.0
Platform: UNKNOWN
Classifier: Intended Audience :: Information Technology
Classifier: Topic :: Security
Classifier: License :: OSI Approved :: GNU General Public License v3 (GPLv3)
Classifier: Programming Language :: Python :: 3
Classifier: Programming Language :: Python :: 3.5
Classifier: Programming Language :: Python :: 3.6
Classifier: Programming Language :: Python :: 3.7
Classifier: Programming Language :: Python :: 3.8
Requires-Dist: requests
Requires-Dist: colorama
Requires-Dist: termcolor
Requires-Dist: PyYAML
